flash_pytorch/__init__.py
flash_pytorch/autoregressive_wrapper.py
flash_pytorch/flash_pytorch.py
FLASH_pytorch-0.1.9.dist-info/LICENSE
FLASH_pytorch-0.1.9.dist-info/METADATA
FLASH_pytorch-0.1.9.dist-info/WHEEL
FLASH_pytorch-0.1.9.dist-info/top_level.txt
FLASH_pytorch-0.1.9.dist-info/RECORD
