Metadata-Version: 2.1
Name: FLASH-pytorch
Version: 0.1.9
Summary: FLASH - Transformer Quality in Linear Time - Pytorch
Home-page: https://github.com/lucidrains/FLASH-pytorch
Author: Phil Wang
Author-email: lucidrains@gmail.com
License: MIT
Keywords: artificial intelligence,deep learning,transformers,attention mechanism
Classifier: Development Status :: 4 - Beta
Classifier: Intended Audience :: Developers
Classifier: Topic :: Scientific/Engineering :: Artificial Intelligence
Classifier: License :: OSI Approved :: MIT License
Classifier: Programming Language :: Python :: 3.6
License-File: LICENSE
Requires-Dist: einops >=0.4
Requires-Dist: rotary-embedding-torch >=0.1.5
Requires-Dist: torch >=1.9
